[
  {
    "numeroItem": 1,
    "descricao": "Publicacao no Diario Oficial da  Uniao   DOI",
    "materialOuServico": "S",
    "materialOuServicoNome": "Serviço",
    "valorUnitarioEstimado": 46.26,
    "valorTotal": 23130.0,
    "quantidade": 500.0,
    "unidadeMedida": "Centimetro",
    "orcamentoSigiloso": false,
    "itemCategoriaId": 3,
    "itemCategoriaNome": "Não se aplica",
    "patrimonio": null,
    "codigoRegistroImobiliario": null,
    "criterioJulgamentoId": 1,
    "criterioJulgamentoNome": "Menor preço",
    "situacaoCompraItem": 1,
    "situacaoCompraItemNome": "Em andamento",
    "tipoBeneficio": 5,
    "tipoBeneficioNome": "Não se aplica",
    "incentivoProdutivoBasico": false,
    "dataInclusao": "2026-04-09T16:57:40",
    "dataAtualizacao": "2026-04-09T16:57:40",
    "temResultado": false,
    "imagem": 0,
    "aplicabilidadeMargemPreferenciaNormal": false,
    "aplicabilidadeMargemPreferenciaAdicional": false,
    "percentualMargemPreferenciaNormal": null,
    "percentualMargemPreferenciaAdicional": null,
    "ncmNbsCodigo": null,
    "ncmNbsDescricao": null,
    "catalogo": null,
    "categoriaItemCatalogo": null,
    "catalogoCodigoItem": null,
    "informacaoComplementar": null,
    "tipoMargemPreferencia": null,
    "exigenciaConteudoNacional": false
  },
  {
    "numeroItem": 2,
    "descricao": "Publicacao na Imprensa Oficial do  Estado de Minas Gerais   DOE. ",
    "materialOuServico": "S",
    "materialOuServicoNome": "Serviço",
    "valorUnitarioEstimado": 119.15,
    "valorTotal": 119150.0,
    "quantidade": 1000.0,
    "unidadeMedida": "Centimetro",
    "orcamentoSigiloso": false,
    "itemCategoriaId": 3,
    "itemCategoriaNome": "Não se aplica",
    "patrimonio": null,
    "codigoRegistroImobiliario": null,
    "criterioJulgamentoId": 1,
    "criterioJulgamentoNome": "Menor preço",
    "situacaoCompraItem": 1,
    "situacaoCompraItemNome": "Em andamento",
    "tipoBeneficio": 5,
    "tipoBeneficioNome": "Não se aplica",
    "incentivoProdutivoBasico": false,
    "dataInclusao": "2026-04-09T16:57:40",
    "dataAtualizacao": "2026-04-09T16:57:40",
    "temResultado": false,
    "imagem": 0,
    "aplicabilidadeMargemPreferenciaNormal": false,
    "aplicabilidadeMargemPreferenciaAdicional": false,
    "percentualMargemPreferenciaNormal": null,
    "percentualMargemPreferenciaAdicional": null,
    "ncmNbsCodigo": null,
    "ncmNbsDescricao": null,
    "catalogo": null,
    "categoriaItemCatalogo": null,
    "catalogoCodigoItem": null,
    "informacaoComplementar": null,
    "tipoMargemPreferencia": null,
    "exigenciaConteudoNacional": false
  },
  {
    "numeroItem": 3,
    "descricao": "Publicacao em Jornal de Grande  Circulacao Estadual  tiragem min.  7.000 e versao digital  ",
    "materialOuServico": "S",
    "materialOuServicoNome": "Serviço",
    "valorUnitarioEstimado": 52.45,
    "valorTotal": 104900.0,
    "quantidade": 2000.0,
    "unidadeMedida": "Centimetro",
    "orcamentoSigiloso": false,
    "itemCategoriaId": 3,
    "itemCategoriaNome": "Não se aplica",
    "patrimonio": null,
    "codigoRegistroImobiliario": null,
    "criterioJulgamentoId": 1,
    "criterioJulgamentoNome": "Menor preço",
    "situacaoCompraItem": 1,
    "situacaoCompraItemNome": "Em andamento",
    "tipoBeneficio": 5,
    "tipoBeneficioNome": "Não se aplica",
    "incentivoProdutivoBasico": false,
    "dataInclusao": "2026-04-09T16:57:40",
    "dataAtualizacao": "2026-04-09T16:57:40",
    "temResultado": false,
    "imagem": 0,
    "aplicabilidadeMargemPreferenciaNormal": false,
    "aplicabilidadeMargemPreferenciaAdicional": false,
    "percentualMargemPreferenciaNormal": null,
    "percentualMargemPreferenciaAdicional": null,
    "ncmNbsCodigo": null,
    "ncmNbsDescricao": null,
    "catalogo": null,
    "categoriaItemCatalogo": null,
    "catalogoCodigoItem": null,
    "informacaoComplementar": null,
    "tipoMargemPreferencia": null,
    "exigenciaConteudoNacional": false
  },
  {
    "numeroItem": 4,
    "descricao": "Publicacao em Jornal de Circulacao  Local Regional  tiragem min.  4.000 e versao digital  ",
    "materialOuServico": "S",
    "materialOuServicoNome": "Serviço",
    "valorUnitarioEstimado": 35.01,
    "valorTotal": 140040.0,
    "quantidade": 4000.0,
    "unidadeMedida": "Centimetro",
    "orcamentoSigiloso": false,
    "itemCategoriaId": 3,
    "itemCategoriaNome": "Não se aplica",
    "patrimonio": null,
    "codigoRegistroImobiliario": null,
    "criterioJulgamentoId": 1,
    "criterioJulgamentoNome": "Menor preço",
    "situacaoCompraItem": 1,
    "situacaoCompraItemNome": "Em andamento",
    "tipoBeneficio": 5,
    "tipoBeneficioNome": "Não se aplica",
    "incentivoProdutivoBasico": false,
    "dataInclusao": "2026-04-09T16:57:40",
    "dataAtualizacao": "2026-04-09T16:57:40",
    "temResultado": false,
    "imagem": 0,
    "aplicabilidadeMargemPreferenciaNormal": false,
    "aplicabilidadeMargemPreferenciaAdicional": false,
    "percentualMargemPreferenciaNormal": null,
    "percentualMargemPreferenciaAdicional": null,
    "ncmNbsCodigo": null,
    "ncmNbsDescricao": null,
    "catalogo": null,
    "categoriaItemCatalogo": null,
    "catalogoCodigoItem": null,
    "informacaoComplementar": null,
    "tipoMargemPreferencia": null,
    "exigenciaConteudoNacional": false
  }
]