[
  {
    "numeroItem": 1,
    "descricao": "Computador Desktop mini/compacto Básico",
    "materialOuServico": "M",
    "materialOuServicoNome": "Material",
    "valorUnitarioEstimado": 2387.67,
    "valorTotal": 143260.2,
    "quantidade": 60.0,
    "unidadeMedida": "UNIDADE",
    "orcamentoSigiloso": false,
    "itemCategoriaId": 3,
    "itemCategoriaNome": "Não se aplica",
    "patrimonio": null,
    "codigoRegistroImobiliario": null,
    "criterioJulgamentoId": 1,
    "criterioJulgamentoNome": "Menor preço",
    "situacaoCompraItem": 1,
    "situacaoCompraItemNome": "Em andamento",
    "tipoBeneficio": 4,
    "tipoBeneficioNome": "Sem benefício",
    "incentivoProdutivoBasico": false,
    "dataInclusao": "2026-03-11T08:31:22",
    "dataAtualizacao": "2026-03-11T08:31:22",
    "temResultado": false,
    "imagem": 0,
    "aplicabilidadeMargemPreferenciaNormal": false,
    "aplicabilidadeMargemPreferenciaAdicional": false,
    "percentualMargemPreferenciaNormal": null,
    "percentualMargemPreferenciaAdicional": null,
    "ncmNbsCodigo": null,
    "ncmNbsDescricao": null,
    "catalogo": null,
    "categoriaItemCatalogo": null,
    "catalogoCodigoItem": null,
    "informacaoComplementar": null,
    "tipoMargemPreferencia": null,
    "exigenciaConteudoNacional": false
  },
  {
    "numeroItem": 2,
    "descricao": "Computador Desktop mini/compacto Intermediário",
    "materialOuServico": "M",
    "materialOuServicoNome": "Material",
    "valorUnitarioEstimado": 3278.63,
    "valorTotal": 98358.9,
    "quantidade": 30.0,
    "unidadeMedida": "UNIDADE",
    "orcamentoSigiloso": false,
    "itemCategoriaId": 3,
    "itemCategoriaNome": "Não se aplica",
    "patrimonio": null,
    "codigoRegistroImobiliario": null,
    "criterioJulgamentoId": 1,
    "criterioJulgamentoNome": "Menor preço",
    "situacaoCompraItem": 1,
    "situacaoCompraItemNome": "Em andamento",
    "tipoBeneficio": 4,
    "tipoBeneficioNome": "Sem benefício",
    "incentivoProdutivoBasico": false,
    "dataInclusao": "2026-03-11T08:31:22",
    "dataAtualizacao": "2026-03-11T08:31:22",
    "temResultado": false,
    "imagem": 0,
    "aplicabilidadeMargemPreferenciaNormal": false,
    "aplicabilidadeMargemPreferenciaAdicional": false,
    "percentualMargemPreferenciaNormal": null,
    "percentualMargemPreferenciaAdicional": null,
    "ncmNbsCodigo": null,
    "ncmNbsDescricao": null,
    "catalogo": null,
    "categoriaItemCatalogo": null,
    "catalogoCodigoItem": null,
    "informacaoComplementar": null,
    "tipoMargemPreferencia": null,
    "exigenciaConteudoNacional": false
  },
  {
    "numeroItem": 3,
    "descricao": "Notebook Administrativo",
    "materialOuServico": "M",
    "materialOuServicoNome": "Material",
    "valorUnitarioEstimado": 4375.2,
    "valorTotal": 87504.0,
    "quantidade": 20.0,
    "unidadeMedida": "UNIDADE",
    "orcamentoSigiloso": false,
    "itemCategoriaId": 3,
    "itemCategoriaNome": "Não se aplica",
    "patrimonio": null,
    "codigoRegistroImobiliario": null,
    "criterioJulgamentoId": 1,
    "criterioJulgamentoNome": "Menor preço",
    "situacaoCompraItem": 1,
    "situacaoCompraItemNome": "Em andamento",
    "tipoBeneficio": 4,
    "tipoBeneficioNome": "Sem benefício",
    "incentivoProdutivoBasico": false,
    "dataInclusao": "2026-03-11T08:31:22",
    "dataAtualizacao": "2026-03-11T08:31:22",
    "temResultado": false,
    "imagem": 0,
    "aplicabilidadeMargemPreferenciaNormal": false,
    "aplicabilidadeMargemPreferenciaAdicional": false,
    "percentualMargemPreferenciaNormal": null,
    "percentualMargemPreferenciaAdicional": null,
    "ncmNbsCodigo": null,
    "ncmNbsDescricao": null,
    "catalogo": null,
    "categoriaItemCatalogo": null,
    "catalogoCodigoItem": null,
    "informacaoComplementar": null,
    "tipoMargemPreferencia": null,
    "exigenciaConteudoNacional": false
  },
  {
    "numeroItem": 4,
    "descricao": "Smartphone",
    "materialOuServico": "M",
    "materialOuServicoNome": "Material",
    "valorUnitarioEstimado": 1211.33,
    "valorTotal": 24226.6,
    "quantidade": 20.0,
    "unidadeMedida": "UNIDADE",
    "orcamentoSigiloso": false,
    "itemCategoriaId": 3,
    "itemCategoriaNome": "Não se aplica",
    "patrimonio": null,
    "codigoRegistroImobiliario": null,
    "criterioJulgamentoId": 1,
    "criterioJulgamentoNome": "Menor preço",
    "situacaoCompraItem": 1,
    "situacaoCompraItemNome": "Em andamento",
    "tipoBeneficio": 1,
    "tipoBeneficioNome": "Participação exclusiva para ME/EPP",
    "incentivoProdutivoBasico": false,
    "dataInclusao": "2026-03-11T08:31:22",
    "dataAtualizacao": "2026-03-11T08:31:22",
    "temResultado": false,
    "imagem": 0,
    "aplicabilidadeMargemPreferenciaNormal": false,
    "aplicabilidadeMargemPreferenciaAdicional": false,
    "percentualMargemPreferenciaNormal": null,
    "percentualMargemPreferenciaAdicional": null,
    "ncmNbsCodigo": null,
    "ncmNbsDescricao": null,
    "catalogo": null,
    "categoriaItemCatalogo": null,
    "catalogoCodigoItem": null,
    "informacaoComplementar": null,
    "tipoMargemPreferencia": null,
    "exigenciaConteudoNacional": false
  },
  {
    "numeroItem": 5,
    "descricao": "Tablet",
    "materialOuServico": "M",
    "materialOuServicoNome": "Material",
    "valorUnitarioEstimado": 1628.01,
    "valorTotal": 32560.2,
    "quantidade": 20.0,
    "unidadeMedida": "UNIDADE",
    "orcamentoSigiloso": false,
    "itemCategoriaId": 3,
    "itemCategoriaNome": "Não se aplica",
    "patrimonio": null,
    "codigoRegistroImobiliario": null,
    "criterioJulgamentoId": 1,
    "criterioJulgamentoNome": "Menor preço",
    "situacaoCompraItem": 1,
    "situacaoCompraItemNome": "Em andamento",
    "tipoBeneficio": 1,
    "tipoBeneficioNome": "Participação exclusiva para ME/EPP",
    "incentivoProdutivoBasico": false,
    "dataInclusao": "2026-03-11T08:31:22",
    "dataAtualizacao": "2026-03-11T08:31:22",
    "temResultado": false,
    "imagem": 0,
    "aplicabilidadeMargemPreferenciaNormal": false,
    "aplicabilidadeMargemPreferenciaAdicional": false,
    "percentualMargemPreferenciaNormal": null,
    "percentualMargemPreferenciaAdicional": null,
    "ncmNbsCodigo": null,
    "ncmNbsDescricao": null,
    "catalogo": null,
    "categoriaItemCatalogo": null,
    "catalogoCodigoItem": null,
    "informacaoComplementar": null,
    "tipoMargemPreferencia": null,
    "exigenciaConteudoNacional": false
  },
  {
    "numeroItem": 6,
    "descricao": "Monitor LED",
    "materialOuServico": "M",
    "materialOuServicoNome": "Material",
    "valorUnitarioEstimado": 862.33,
    "valorTotal": 60363.1,
    "quantidade": 70.0,
    "unidadeMedida": "UNIDADE",
    "orcamentoSigiloso": false,
    "itemCategoriaId": 3,
    "itemCategoriaNome": "Não se aplica",
    "patrimonio": null,
    "codigoRegistroImobiliario": null,
    "criterioJulgamentoId": 1,
    "criterioJulgamentoNome": "Menor preço",
    "situacaoCompraItem": 1,
    "situacaoCompraItemNome": "Em andamento",
    "tipoBeneficio": 1,
    "tipoBeneficioNome": "Participação exclusiva para ME/EPP",
    "incentivoProdutivoBasico": false,
    "dataInclusao": "2026-03-11T08:31:22",
    "dataAtualizacao": "2026-03-11T08:31:22",
    "temResultado": false,
    "imagem": 0,
    "aplicabilidadeMargemPreferenciaNormal": false,
    "aplicabilidadeMargemPreferenciaAdicional": false,
    "percentualMargemPreferenciaNormal": null,
    "percentualMargemPreferenciaAdicional": null,
    "ncmNbsCodigo": null,
    "ncmNbsDescricao": null,
    "catalogo": null,
    "categoriaItemCatalogo": null,
    "catalogoCodigoItem": null,
    "informacaoComplementar": null,
    "tipoMargemPreferencia": null,
    "exigenciaConteudoNacional": false
  },
  {
    "numeroItem": 7,
    "descricao": "Teclado USB ABNT2",
    "materialOuServico": "M",
    "materialOuServicoNome": "Material",
    "valorUnitarioEstimado": 75.18,
    "valorTotal": 5262.6,
    "quantidade": 70.0,
    "unidadeMedida": "UNIDADE",
    "orcamentoSigiloso": false,
    "itemCategoriaId": 3,
    "itemCategoriaNome": "Não se aplica",
    "patrimonio": null,
    "codigoRegistroImobiliario": null,
    "criterioJulgamentoId": 1,
    "criterioJulgamentoNome": "Menor preço",
    "situacaoCompraItem": 1,
    "situacaoCompraItemNome": "Em andamento",
    "tipoBeneficio": 1,
    "tipoBeneficioNome": "Participação exclusiva para ME/EPP",
    "incentivoProdutivoBasico": false,
    "dataInclusao": "2026-03-11T08:31:22",
    "dataAtualizacao": "2026-03-11T08:31:22",
    "temResultado": false,
    "imagem": 0,
    "aplicabilidadeMargemPreferenciaNormal": false,
    "aplicabilidadeMargemPreferenciaAdicional": false,
    "percentualMargemPreferenciaNormal": null,
    "percentualMargemPreferenciaAdicional": null,
    "ncmNbsCodigo": null,
    "ncmNbsDescricao": null,
    "catalogo": null,
    "categoriaItemCatalogo": null,
    "catalogoCodigoItem": null,
    "informacaoComplementar": null,
    "tipoMargemPreferencia": null,
    "exigenciaConteudoNacional": false
  },
  {
    "numeroItem": 8,
    "descricao": "Mouse USB Óptico",
    "materialOuServico": "M",
    "materialOuServicoNome": "Material",
    "valorUnitarioEstimado": 76.8,
    "valorTotal": 5376.0,
    "quantidade": 70.0,
    "unidadeMedida": "UNIDADE",
    "orcamentoSigiloso": false,
    "itemCategoriaId": 3,
    "itemCategoriaNome": "Não se aplica",
    "patrimonio": null,
    "codigoRegistroImobiliario": null,
    "criterioJulgamentoId": 1,
    "criterioJulgamentoNome": "Menor preço",
    "situacaoCompraItem": 1,
    "situacaoCompraItemNome": "Em andamento",
    "tipoBeneficio": 1,
    "tipoBeneficioNome": "Participação exclusiva para ME/EPP",
    "incentivoProdutivoBasico": false,
    "dataInclusao": "2026-03-11T08:31:22",
    "dataAtualizacao": "2026-03-11T08:31:22",
    "temResultado": false,
    "imagem": 0,
    "aplicabilidadeMargemPreferenciaNormal": false,
    "aplicabilidadeMargemPreferenciaAdicional": false,
    "percentualMargemPreferenciaNormal": null,
    "percentualMargemPreferenciaAdicional": null,
    "ncmNbsCodigo": null,
    "ncmNbsDescricao": null,
    "catalogo": null,
    "categoriaItemCatalogo": null,
    "catalogoCodigoItem": null,
    "informacaoComplementar": null,
    "tipoMargemPreferencia": null,
    "exigenciaConteudoNacional": false
  },
  {
    "numeroItem": 9,
    "descricao": "MOUSE OPTICO SEM FIO",
    "materialOuServico": "M",
    "materialOuServicoNome": "Material",
    "valorUnitarioEstimado": 99.34,
    "valorTotal": 4967.0,
    "quantidade": 50.0,
    "unidadeMedida": "UNIDADE",
    "orcamentoSigiloso": false,
    "itemCategoriaId": 3,
    "itemCategoriaNome": "Não se aplica",
    "patrimonio": null,
    "codigoRegistroImobiliario": null,
    "criterioJulgamentoId": 1,
    "criterioJulgamentoNome": "Menor preço",
    "situacaoCompraItem": 1,
    "situacaoCompraItemNome": "Em andamento",
    "tipoBeneficio": 1,
    "tipoBeneficioNome": "Participação exclusiva para ME/EPP",
    "incentivoProdutivoBasico": false,
    "dataInclusao": "2026-03-11T08:31:22",
    "dataAtualizacao": "2026-03-11T08:31:22",
    "temResultado": false,
    "imagem": 0,
    "aplicabilidadeMargemPreferenciaNormal": false,
    "aplicabilidadeMargemPreferenciaAdicional": false,
    "percentualMargemPreferenciaNormal": null,
    "percentualMargemPreferenciaAdicional": null,
    "ncmNbsCodigo": null,
    "ncmNbsDescricao": null,
    "catalogo": null,
    "categoriaItemCatalogo": null,
    "catalogoCodigoItem": null,
    "informacaoComplementar": null,
    "tipoMargemPreferencia": null,
    "exigenciaConteudoNacional": false
  },
  {
    "numeroItem": 10,
    "descricao": "MOUSEPAD COM APOIO DE PUNHO",
    "materialOuServico": "M",
    "materialOuServicoNome": "Material",
    "valorUnitarioEstimado": 57.64,
    "valorTotal": 2882.0,
    "quantidade": 50.0,
    "unidadeMedida": "UNIDADE",
    "orcamentoSigiloso": false,
    "itemCategoriaId": 3,
    "itemCategoriaNome": "Não se aplica",
    "patrimonio": null,
    "codigoRegistroImobiliario": null,
    "criterioJulgamentoId": 1,
    "criterioJulgamentoNome": "Menor preço",
    "situacaoCompraItem": 1,
    "situacaoCompraItemNome": "Em andamento",
    "tipoBeneficio": 1,
    "tipoBeneficioNome": "Participação exclusiva para ME/EPP",
    "incentivoProdutivoBasico": false,
    "dataInclusao": "2026-03-11T08:31:22",
    "dataAtualizacao": "2026-03-11T08:31:22",
    "temResultado": false,
    "imagem": 0,
    "aplicabilidadeMargemPreferenciaNormal": false,
    "aplicabilidadeMargemPreferenciaAdicional": false,
    "percentualMargemPreferenciaNormal": null,
    "percentualMargemPreferenciaAdicional": null,
    "ncmNbsCodigo": null,
    "ncmNbsDescricao": null,
    "catalogo": null,
    "categoriaItemCatalogo": null,
    "catalogoCodigoItem": null,
    "informacaoComplementar": null,
    "tipoMargemPreferencia": null,
    "exigenciaConteudoNacional": false
  },
  {
    "numeroItem": 11,
    "descricao": "PROJETOR MULTIMIDIA",
    "materialOuServico": "M",
    "materialOuServicoNome": "Material",
    "valorUnitarioEstimado": 2742.12,
    "valorTotal": 13710.6,
    "quantidade": 5.0,
    "unidadeMedida": "UNIDADE",
    "orcamentoSigiloso": false,
    "itemCategoriaId": 3,
    "itemCategoriaNome": "Não se aplica",
    "patrimonio": null,
    "codigoRegistroImobiliario": null,
    "criterioJulgamentoId": 1,
    "criterioJulgamentoNome": "Menor preço",
    "situacaoCompraItem": 1,
    "situacaoCompraItemNome": "Em andamento",
    "tipoBeneficio": 1,
    "tipoBeneficioNome": "Participação exclusiva para ME/EPP",
    "incentivoProdutivoBasico": false,
    "dataInclusao": "2026-03-11T08:31:22",
    "dataAtualizacao": "2026-03-11T08:31:22",
    "temResultado": false,
    "imagem": 0,
    "aplicabilidadeMargemPreferenciaNormal": false,
    "aplicabilidadeMargemPreferenciaAdicional": false,
    "percentualMargemPreferenciaNormal": null,
    "percentualMargemPreferenciaAdicional": null,
    "ncmNbsCodigo": null,
    "ncmNbsDescricao": null,
    "catalogo": null,
    "categoriaItemCatalogo": null,
    "catalogoCodigoItem": null,
    "informacaoComplementar": null,
    "tipoMargemPreferencia": null,
    "exigenciaConteudoNacional": false
  },
  {
    "numeroItem": 12,
    "descricao": "TELA RETRATIL PARA PROJETOR",
    "materialOuServico": "M",
    "materialOuServicoNome": "Material",
    "valorUnitarioEstimado": 862.81,
    "valorTotal": 4314.05,
    "quantidade": 5.0,
    "unidadeMedida": "UNIDADE",
    "orcamentoSigiloso": false,
    "itemCategoriaId": 3,
    "itemCategoriaNome": "Não se aplica",
    "patrimonio": null,
    "codigoRegistroImobiliario": null,
    "criterioJulgamentoId": 1,
    "criterioJulgamentoNome": "Menor preço",
    "situacaoCompraItem": 1,
    "situacaoCompraItemNome": "Em andamento",
    "tipoBeneficio": 1,
    "tipoBeneficioNome": "Participação exclusiva para ME/EPP",
    "incentivoProdutivoBasico": false,
    "dataInclusao": "2026-03-11T08:31:22",
    "dataAtualizacao": "2026-03-11T08:31:22",
    "temResultado": false,
    "imagem": 0,
    "aplicabilidadeMargemPreferenciaNormal": false,
    "aplicabilidadeMargemPreferenciaAdicional": false,
    "percentualMargemPreferenciaNormal": null,
    "percentualMargemPreferenciaAdicional": null,
    "ncmNbsCodigo": null,
    "ncmNbsDescricao": null,
    "catalogo": null,
    "categoriaItemCatalogo": null,
    "catalogoCodigoItem": null,
    "informacaoComplementar": null,
    "tipoMargemPreferencia": null,
    "exigenciaConteudoNacional": false
  },
  {
    "numeroItem": 13,
    "descricao": "Case/adaptador para HD",
    "materialOuServico": "M",
    "materialOuServicoNome": "Material",
    "valorUnitarioEstimado": 54.5,
    "valorTotal": 1635.0,
    "quantidade": 30.0,
    "unidadeMedida": "UNIDADE",
    "orcamentoSigiloso": false,
    "itemCategoriaId": 3,
    "itemCategoriaNome": "Não se aplica",
    "patrimonio": null,
    "codigoRegistroImobiliario": null,
    "criterioJulgamentoId": 1,
    "criterioJulgamentoNome": "Menor preço",
    "situacaoCompraItem": 1,
    "situacaoCompraItemNome": "Em andamento",
    "tipoBeneficio": 1,
    "tipoBeneficioNome": "Participação exclusiva para ME/EPP",
    "incentivoProdutivoBasico": false,
    "dataInclusao": "2026-03-11T08:31:22",
    "dataAtualizacao": "2026-03-11T08:31:22",
    "temResultado": false,
    "imagem": 0,
    "aplicabilidadeMargemPreferenciaNormal": false,
    "aplicabilidadeMargemPreferenciaAdicional": false,
    "percentualMargemPreferenciaNormal": null,
    "percentualMargemPreferenciaAdicional": null,
    "ncmNbsCodigo": null,
    "ncmNbsDescricao": null,
    "catalogo": null,
    "categoriaItemCatalogo": null,
    "catalogoCodigoItem": null,
    "informacaoComplementar": null,
    "tipoMargemPreferencia": null,
    "exigenciaConteudoNacional": false
  },
  {
    "numeroItem": 14,
    "descricao": "Webcam Full HD",
    "materialOuServico": "M",
    "materialOuServicoNome": "Material",
    "valorUnitarioEstimado": 285.65,
    "valorTotal": 8569.5,
    "quantidade": 30.0,
    "unidadeMedida": "UNIDADE",
    "orcamentoSigiloso": false,
    "itemCategoriaId": 3,
    "itemCategoriaNome": "Não se aplica",
    "patrimonio": null,
    "codigoRegistroImobiliario": null,
    "criterioJulgamentoId": 1,
    "criterioJulgamentoNome": "Menor preço",
    "situacaoCompraItem": 1,
    "situacaoCompraItemNome": "Em andamento",
    "tipoBeneficio": 1,
    "tipoBeneficioNome": "Participação exclusiva para ME/EPP",
    "incentivoProdutivoBasico": false,
    "dataInclusao": "2026-03-11T08:31:22",
    "dataAtualizacao": "2026-03-11T08:31:22",
    "temResultado": false,
    "imagem": 0,
    "aplicabilidadeMargemPreferenciaNormal": false,
    "aplicabilidadeMargemPreferenciaAdicional": false,
    "percentualMargemPreferenciaNormal": null,
    "percentualMargemPreferenciaAdicional": null,
    "ncmNbsCodigo": null,
    "ncmNbsDescricao": null,
    "catalogo": null,
    "categoriaItemCatalogo": null,
    "catalogoCodigoItem": null,
    "informacaoComplementar": null,
    "tipoMargemPreferencia": null,
    "exigenciaConteudoNacional": false
  },
  {
    "numeroItem": 15,
    "descricao": "Caixas de Som Simples (uso em escritório)",
    "materialOuServico": "M",
    "materialOuServicoNome": "Material",
    "valorUnitarioEstimado": 34.57,
    "valorTotal": 691.4,
    "quantidade": 20.0,
    "unidadeMedida": "UNIDADE",
    "orcamentoSigiloso": false,
    "itemCategoriaId": 3,
    "itemCategoriaNome": "Não se aplica",
    "patrimonio": null,
    "codigoRegistroImobiliario": null,
    "criterioJulgamentoId": 1,
    "criterioJulgamentoNome": "Menor preço",
    "situacaoCompraItem": 1,
    "situacaoCompraItemNome": "Em andamento",
    "tipoBeneficio": 1,
    "tipoBeneficioNome": "Participação exclusiva para ME/EPP",
    "incentivoProdutivoBasico": false,
    "dataInclusao": "2026-03-11T08:31:22",
    "dataAtualizacao": "2026-03-11T08:31:22",
    "temResultado": false,
    "imagem": 0,
    "aplicabilidadeMargemPreferenciaNormal": false,
    "aplicabilidadeMargemPreferenciaAdicional": false,
    "percentualMargemPreferenciaNormal": null,
    "percentualMargemPreferenciaAdicional": null,
    "ncmNbsCodigo": null,
    "ncmNbsDescricao": null,
    "catalogo": null,
    "categoriaItemCatalogo": null,
    "catalogoCodigoItem": null,
    "informacaoComplementar": null,
    "tipoMargemPreferencia": null,
    "exigenciaConteudoNacional": false
  },
  {
    "numeroItem": 16,
    "descricao": "Headset USB",
    "materialOuServico": "M",
    "materialOuServicoNome": "Material",
    "valorUnitarioEstimado": 139.67,
    "valorTotal": 1396.7,
    "quantidade": 10.0,
    "unidadeMedida": "UNIDADE",
    "orcamentoSigiloso": false,
    "itemCategoriaId": 3,
    "itemCategoriaNome": "Não se aplica",
    "patrimonio": null,
    "codigoRegistroImobiliario": null,
    "criterioJulgamentoId": 1,
    "criterioJulgamentoNome": "Menor preço",
    "situacaoCompraItem": 1,
    "situacaoCompraItemNome": "Em andamento",
    "tipoBeneficio": 1,
    "tipoBeneficioNome": "Participação exclusiva para ME/EPP",
    "incentivoProdutivoBasico": false,
    "dataInclusao": "2026-03-11T08:31:22",
    "dataAtualizacao": "2026-03-11T08:31:22",
    "temResultado": false,
    "imagem": 0,
    "aplicabilidadeMargemPreferenciaNormal": false,
    "aplicabilidadeMargemPreferenciaAdicional": false,
    "percentualMargemPreferenciaNormal": null,
    "percentualMargemPreferenciaAdicional": null,
    "ncmNbsCodigo": null,
    "ncmNbsDescricao": null,
    "catalogo": null,
    "categoriaItemCatalogo": null,
    "catalogoCodigoItem": null,
    "informacaoComplementar": null,
    "tipoMargemPreferencia": null,
    "exigenciaConteudoNacional": false
  },
  {
    "numeroItem": 17,
    "descricao": "Pen drive 32GB",
    "materialOuServico": "M",
    "materialOuServicoNome": "Material",
    "valorUnitarioEstimado": 55.31,
    "valorTotal": 2765.5,
    "quantidade": 50.0,
    "unidadeMedida": "UNIDADE",
    "orcamentoSigiloso": false,
    "itemCategoriaId": 3,
    "itemCategoriaNome": "Não se aplica",
    "patrimonio": null,
    "codigoRegistroImobiliario": null,
    "criterioJulgamentoId": 1,
    "criterioJulgamentoNome": "Menor preço",
    "situacaoCompraItem": 1,
    "situacaoCompraItemNome": "Em andamento",
    "tipoBeneficio": 1,
    "tipoBeneficioNome": "Participação exclusiva para ME/EPP",
    "incentivoProdutivoBasico": false,
    "dataInclusao": "2026-03-11T08:31:22",
    "dataAtualizacao": "2026-03-11T08:31:22",
    "temResultado": false,
    "imagem": 0,
    "aplicabilidadeMargemPreferenciaNormal": false,
    "aplicabilidadeMargemPreferenciaAdicional": false,
    "percentualMargemPreferenciaNormal": null,
    "percentualMargemPreferenciaAdicional": null,
    "ncmNbsCodigo": null,
    "ncmNbsDescricao": null,
    "catalogo": null,
    "categoriaItemCatalogo": null,
    "catalogoCodigoItem": null,
    "informacaoComplementar": null,
    "tipoMargemPreferencia": null,
    "exigenciaConteudoNacional": false
  },
  {
    "numeroItem": 18,
    "descricao": "Adaptador Wi-Fi USB",
    "materialOuServico": "M",
    "materialOuServicoNome": "Material",
    "valorUnitarioEstimado": 57.9,
    "valorTotal": 1158.0,
    "quantidade": 20.0,
    "unidadeMedida": "UNIDADE",
    "orcamentoSigiloso": false,
    "itemCategoriaId": 3,
    "itemCategoriaNome": "Não se aplica",
    "patrimonio": null,
    "codigoRegistroImobiliario": null,
    "criterioJulgamentoId": 1,
    "criterioJulgamentoNome": "Menor preço",
    "situacaoCompraItem": 1,
    "situacaoCompraItemNome": "Em andamento",
    "tipoBeneficio": 1,
    "tipoBeneficioNome": "Participação exclusiva para ME/EPP",
    "incentivoProdutivoBasico": false,
    "dataInclusao": "2026-03-11T08:31:22",
    "dataAtualizacao": "2026-03-11T08:31:22",
    "temResultado": false,
    "imagem": 0,
    "aplicabilidadeMargemPreferenciaNormal": false,
    "aplicabilidadeMargemPreferenciaAdicional": false,
    "percentualMargemPreferenciaNormal": null,
    "percentualMargemPreferenciaAdicional": null,
    "ncmNbsCodigo": null,
    "ncmNbsDescricao": null,
    "catalogo": null,
    "categoriaItemCatalogo": null,
    "catalogoCodigoItem": null,
    "informacaoComplementar": null,
    "tipoMargemPreferencia": null,
    "exigenciaConteudoNacional": false
  },
  {
    "numeroItem": 19,
    "descricao": "Cabo HDMI.",
    "materialOuServico": "M",
    "materialOuServicoNome": "Material",
    "valorUnitarioEstimado": 24.33,
    "valorTotal": 486.6,
    "quantidade": 20.0,
    "unidadeMedida": "METRO",
    "orcamentoSigiloso": false,
    "itemCategoriaId": 3,
    "itemCategoriaNome": "Não se aplica",
    "patrimonio": null,
    "codigoRegistroImobiliario": null,
    "criterioJulgamentoId": 1,
    "criterioJulgamentoNome": "Menor preço",
    "situacaoCompraItem": 1,
    "situacaoCompraItemNome": "Em andamento",
    "tipoBeneficio": 1,
    "tipoBeneficioNome": "Participação exclusiva para ME/EPP",
    "incentivoProdutivoBasico": false,
    "dataInclusao": "2026-03-11T08:31:22",
    "dataAtualizacao": "2026-03-11T08:31:22",
    "temResultado": false,
    "imagem": 0,
    "aplicabilidadeMargemPreferenciaNormal": false,
    "aplicabilidadeMargemPreferenciaAdicional": false,
    "percentualMargemPreferenciaNormal": null,
    "percentualMargemPreferenciaAdicional": null,
    "ncmNbsCodigo": null,
    "ncmNbsDescricao": null,
    "catalogo": null,
    "categoriaItemCatalogo": null,
    "catalogoCodigoItem": null,
    "informacaoComplementar": null,
    "tipoMargemPreferencia": null,
    "exigenciaConteudoNacional": false
  },
  {
    "numeroItem": 20,
    "descricao": "Cabo HDMI",
    "materialOuServico": "M",
    "materialOuServicoNome": "Material",
    "valorUnitarioEstimado": 19.92,
    "valorTotal": 398.4,
    "quantidade": 20.0,
    "unidadeMedida": "METRO",
    "orcamentoSigiloso": false,
    "itemCategoriaId": 3,
    "itemCategoriaNome": "Não se aplica",
    "patrimonio": null,
    "codigoRegistroImobiliario": null,
    "criterioJulgamentoId": 1,
    "criterioJulgamentoNome": "Menor preço",
    "situacaoCompraItem": 1,
    "situacaoCompraItemNome": "Em andamento",
    "tipoBeneficio": 1,
    "tipoBeneficioNome": "Participação exclusiva para ME/EPP",
    "incentivoProdutivoBasico": false,
    "dataInclusao": "2026-03-11T08:31:22",
    "dataAtualizacao": "2026-03-11T08:31:22",
    "temResultado": false,
    "imagem": 0,
    "aplicabilidadeMargemPreferenciaNormal": false,
    "aplicabilidadeMargemPreferenciaAdicional": false,
    "percentualMargemPreferenciaNormal": null,
    "percentualMargemPreferenciaAdicional": null,
    "ncmNbsCodigo": null,
    "ncmNbsDescricao": null,
    "catalogo": null,
    "categoriaItemCatalogo": null,
    "catalogoCodigoItem": null,
    "informacaoComplementar": null,
    "tipoMargemPreferencia": null,
    "exigenciaConteudoNacional": false
  },
  {
    "numeroItem": 21,
    "descricao": "Memória DDR3 8GB 1333MHz",
    "materialOuServico": "M",
    "materialOuServicoNome": "Material",
    "valorUnitarioEstimado": 303.75,
    "valorTotal": 9112.5,
    "quantidade": 30.0,
    "unidadeMedida": "UNIDADE",
    "orcamentoSigiloso": false,
    "itemCategoriaId": 3,
    "itemCategoriaNome": "Não se aplica",
    "patrimonio": null,
    "codigoRegistroImobiliario": null,
    "criterioJulgamentoId": 1,
    "criterioJulgamentoNome": "Menor preço",
    "situacaoCompraItem": 1,
    "situacaoCompraItemNome": "Em andamento",
    "tipoBeneficio": 1,
    "tipoBeneficioNome": "Participação exclusiva para ME/EPP",
    "incentivoProdutivoBasico": false,
    "dataInclusao": "2026-03-11T08:31:22",
    "dataAtualizacao": "2026-03-11T08:31:22",
    "temResultado": false,
    "imagem": 0,
    "aplicabilidadeMargemPreferenciaNormal": false,
    "aplicabilidadeMargemPreferenciaAdicional": false,
    "percentualMargemPreferenciaNormal": null,
    "percentualMargemPreferenciaAdicional": null,
    "ncmNbsCodigo": null,
    "ncmNbsDescricao": null,
    "catalogo": null,
    "categoriaItemCatalogo": null,
    "catalogoCodigoItem": null,
    "informacaoComplementar": null,
    "tipoMargemPreferencia": null,
    "exigenciaConteudoNacional": false
  },
  {
    "numeroItem": 22,
    "descricao": "Memória DDR4 8GB 2400MHz ou superior",
    "materialOuServico": "M",
    "materialOuServicoNome": "Material",
    "valorUnitarioEstimado": 163.32,
    "valorTotal": 4899.6,
    "quantidade": 30.0,
    "unidadeMedida": "UNIDADE",
    "orcamentoSigiloso": false,
    "itemCategoriaId": 3,
    "itemCategoriaNome": "Não se aplica",
    "patrimonio": null,
    "codigoRegistroImobiliario": null,
    "criterioJulgamentoId": 1,
    "criterioJulgamentoNome": "Menor preço",
    "situacaoCompraItem": 1,
    "situacaoCompraItemNome": "Em andamento",
    "tipoBeneficio": 1,
    "tipoBeneficioNome": "Participação exclusiva para ME/EPP",
    "incentivoProdutivoBasico": false,
    "dataInclusao": "2026-03-11T08:31:22",
    "dataAtualizacao": "2026-03-11T08:31:22",
    "temResultado": false,
    "imagem": 0,
    "aplicabilidadeMargemPreferenciaNormal": false,
    "aplicabilidadeMargemPreferenciaAdicional": false,
    "percentualMargemPreferenciaNormal": null,
    "percentualMargemPreferenciaAdicional": null,
    "ncmNbsCodigo": null,
    "ncmNbsDescricao": null,
    "catalogo": null,
    "categoriaItemCatalogo": null,
    "catalogoCodigoItem": null,
    "informacaoComplementar": null,
    "tipoMargemPreferencia": null,
    "exigenciaConteudoNacional": false
  },
  {
    "numeroItem": 23,
    "descricao": "Placa de Rede PCI-e Gigabit",
    "materialOuServico": "M",
    "materialOuServicoNome": "Material",
    "valorUnitarioEstimado": 219.0,
    "valorTotal": 6570.0,
    "quantidade": 30.0,
    "unidadeMedida": "UNIDADE",
    "orcamentoSigiloso": false,
    "itemCategoriaId": 3,
    "itemCategoriaNome": "Não se aplica",
    "patrimonio": null,
    "codigoRegistroImobiliario": null,
    "criterioJulgamentoId": 1,
    "criterioJulgamentoNome": "Menor preço",
    "situacaoCompraItem": 1,
    "situacaoCompraItemNome": "Em andamento",
    "tipoBeneficio": 1,
    "tipoBeneficioNome": "Participação exclusiva para ME/EPP",
    "incentivoProdutivoBasico": false,
    "dataInclusao": "2026-03-11T08:31:22",
    "dataAtualizacao": "2026-03-11T08:31:22",
    "temResultado": false,
    "imagem": 0,
    "aplicabilidadeMargemPreferenciaNormal": false,
    "aplicabilidadeMargemPreferenciaAdicional": false,
    "percentualMargemPreferenciaNormal": null,
    "percentualMargemPreferenciaAdicional": null,
    "ncmNbsCodigo": null,
    "ncmNbsDescricao": null,
    "catalogo": null,
    "categoriaItemCatalogo": null,
    "catalogoCodigoItem": null,
    "informacaoComplementar": null,
    "tipoMargemPreferencia": null,
    "exigenciaConteudoNacional": false
  },
  {
    "numeroItem": 24,
    "descricao": "Placa de Vídeo PCI-Express Básica",
    "materialOuServico": "M",
    "materialOuServicoNome": "Material",
    "valorUnitarioEstimado": 82.82,
    "valorTotal": 1242.3,
    "quantidade": 15.0,
    "unidadeMedida": "UNIDADE",
    "orcamentoSigiloso": false,
    "itemCategoriaId": 3,
    "itemCategoriaNome": "Não se aplica",
    "patrimonio": null,
    "codigoRegistroImobiliario": null,
    "criterioJulgamentoId": 1,
    "criterioJulgamentoNome": "Menor preço",
    "situacaoCompraItem": 1,
    "situacaoCompraItemNome": "Em andamento",
    "tipoBeneficio": 1,
    "tipoBeneficioNome": "Participação exclusiva para ME/EPP",
    "incentivoProdutivoBasico": false,
    "dataInclusao": "2026-03-11T08:31:22",
    "dataAtualizacao": "2026-03-11T08:31:22",
    "temResultado": false,
    "imagem": 0,
    "aplicabilidadeMargemPreferenciaNormal": false,
    "aplicabilidadeMargemPreferenciaAdicional": false,
    "percentualMargemPreferenciaNormal": null,
    "percentualMargemPreferenciaAdicional": null,
    "ncmNbsCodigo": null,
    "ncmNbsDescricao": null,
    "catalogo": null,
    "categoriaItemCatalogo": null,
    "catalogoCodigoItem": null,
    "informacaoComplementar": null,
    "tipoMargemPreferencia": null,
    "exigenciaConteudoNacional": false
  },
  {
    "numeroItem": 25,
    "descricao": "Placa-Mãe ATX/µATX",
    "materialOuServico": "M",
    "materialOuServicoNome": "Material",
    "valorUnitarioEstimado": 493.82,
    "valorTotal": 7407.3,
    "quantidade": 15.0,
    "unidadeMedida": "UNIDADE",
    "orcamentoSigiloso": false,
    "itemCategoriaId": 3,
    "itemCategoriaNome": "Não se aplica",
    "patrimonio": null,
    "codigoRegistroImobiliario": null,
    "criterioJulgamentoId": 1,
    "criterioJulgamentoNome": "Menor preço",
    "situacaoCompraItem": 1,
    "situacaoCompraItemNome": "Em andamento",
    "tipoBeneficio": 1,
    "tipoBeneficioNome": "Participação exclusiva para ME/EPP",
    "incentivoProdutivoBasico": false,
    "dataInclusao": "2026-03-11T08:31:22",
    "dataAtualizacao": "2026-03-11T08:31:22",
    "temResultado": false,
    "imagem": 0,
    "aplicabilidadeMargemPreferenciaNormal": false,
    "aplicabilidadeMargemPreferenciaAdicional": false,
    "percentualMargemPreferenciaNormal": null,
    "percentualMargemPreferenciaAdicional": null,
    "ncmNbsCodigo": null,
    "ncmNbsDescricao": null,
    "catalogo": null,
    "categoriaItemCatalogo": null,
    "catalogoCodigoItem": null,
    "informacaoComplementar": null,
    "tipoMargemPreferencia": null,
    "exigenciaConteudoNacional": false
  },
  {
    "numeroItem": 26,
    "descricao": "Fonte 350W Reais",
    "materialOuServico": "M",
    "materialOuServicoNome": "Material",
    "valorUnitarioEstimado": 389.67,
    "valorTotal": 19483.5,
    "quantidade": 50.0,
    "unidadeMedida": "UNIDADE",
    "orcamentoSigiloso": false,
    "itemCategoriaId": 3,
    "itemCategoriaNome": "Não se aplica",
    "patrimonio": null,
    "codigoRegistroImobiliario": null,
    "criterioJulgamentoId": 1,
    "criterioJulgamentoNome": "Menor preço",
    "situacaoCompraItem": 1,
    "situacaoCompraItemNome": "Em andamento",
    "tipoBeneficio": 1,
    "tipoBeneficioNome": "Participação exclusiva para ME/EPP",
    "incentivoProdutivoBasico": false,
    "dataInclusao": "2026-03-11T08:31:22",
    "dataAtualizacao": "2026-03-11T08:31:22",
    "temResultado": false,
    "imagem": 0,
    "aplicabilidadeMargemPreferenciaNormal": false,
    "aplicabilidadeMargemPreferenciaAdicional": false,
    "percentualMargemPreferenciaNormal": null,
    "percentualMargemPreferenciaAdicional": null,
    "ncmNbsCodigo": null,
    "ncmNbsDescricao": null,
    "catalogo": null,
    "categoriaItemCatalogo": null,
    "catalogoCodigoItem": null,
    "informacaoComplementar": null,
    "tipoMargemPreferencia": null,
    "exigenciaConteudoNacional": false
  },
  {
    "numeroItem": 27,
    "descricao": "SSD 240GB SATA",
    "materialOuServico": "M",
    "materialOuServicoNome": "Material",
    "valorUnitarioEstimado": 236.33,
    "valorTotal": 11816.5,
    "quantidade": 50.0,
    "unidadeMedida": "UNIDADE",
    "orcamentoSigiloso": false,
    "itemCategoriaId": 3,
    "itemCategoriaNome": "Não se aplica",
    "patrimonio": null,
    "codigoRegistroImobiliario": null,
    "criterioJulgamentoId": 1,
    "criterioJulgamentoNome": "Menor preço",
    "situacaoCompraItem": 1,
    "situacaoCompraItemNome": "Em andamento",
    "tipoBeneficio": 1,
    "tipoBeneficioNome": "Participação exclusiva para ME/EPP",
    "incentivoProdutivoBasico": false,
    "dataInclusao": "2026-03-11T08:31:22",
    "dataAtualizacao": "2026-03-11T08:31:22",
    "temResultado": false,
    "imagem": 0,
    "aplicabilidadeMargemPreferenciaNormal": false,
    "aplicabilidadeMargemPreferenciaAdicional": false,
    "percentualMargemPreferenciaNormal": null,
    "percentualMargemPreferenciaAdicional": null,
    "ncmNbsCodigo": null,
    "ncmNbsDescricao": null,
    "catalogo": null,
    "categoriaItemCatalogo": null,
    "catalogoCodigoItem": null,
    "informacaoComplementar": null,
    "tipoMargemPreferencia": null,
    "exigenciaConteudoNacional": false
  },
  {
    "numeroItem": 28,
    "descricao": "SSD 480/512GB SATA",
    "materialOuServico": "M",
    "materialOuServicoNome": "Material",
    "valorUnitarioEstimado": 349.67,
    "valorTotal": 13986.8,
    "quantidade": 40.0,
    "unidadeMedida": "UNIDADE",
    "orcamentoSigiloso": false,
    "itemCategoriaId": 3,
    "itemCategoriaNome": "Não se aplica",
    "patrimonio": null,
    "codigoRegistroImobiliario": null,
    "criterioJulgamentoId": 1,
    "criterioJulgamentoNome": "Menor preço",
    "situacaoCompraItem": 1,
    "situacaoCompraItemNome": "Em andamento",
    "tipoBeneficio": 1,
    "tipoBeneficioNome": "Participação exclusiva para ME/EPP",
    "incentivoProdutivoBasico": false,
    "dataInclusao": "2026-03-11T08:31:22",
    "dataAtualizacao": "2026-03-11T08:31:22",
    "temResultado": false,
    "imagem": 0,
    "aplicabilidadeMargemPreferenciaNormal": false,
    "aplicabilidadeMargemPreferenciaAdicional": false,
    "percentualMargemPreferenciaNormal": null,
    "percentualMargemPreferenciaAdicional": null,
    "ncmNbsCodigo": null,
    "ncmNbsDescricao": null,
    "catalogo": null,
    "categoriaItemCatalogo": null,
    "catalogoCodigoItem": null,
    "informacaoComplementar": null,
    "tipoMargemPreferencia": null,
    "exigenciaConteudoNacional": false
  },
  {
    "numeroItem": 29,
    "descricao": "HD Interno 1TB SATA",
    "materialOuServico": "M",
    "materialOuServicoNome": "Material",
    "valorUnitarioEstimado": 332.67,
    "valorTotal": 6653.4,
    "quantidade": 20.0,
    "unidadeMedida": "UNIDADE",
    "orcamentoSigiloso": false,
    "itemCategoriaId": 3,
    "itemCategoriaNome": "Não se aplica",
    "patrimonio": null,
    "codigoRegistroImobiliario": null,
    "criterioJulgamentoId": 1,
    "criterioJulgamentoNome": "Menor preço",
    "situacaoCompraItem": 1,
    "situacaoCompraItemNome": "Em andamento",
    "tipoBeneficio": 1,
    "tipoBeneficioNome": "Participação exclusiva para ME/EPP",
    "incentivoProdutivoBasico": false,
    "dataInclusao": "2026-03-11T08:31:22",
    "dataAtualizacao": "2026-03-11T08:31:22",
    "temResultado": false,
    "imagem": 0,
    "aplicabilidadeMargemPreferenciaNormal": false,
    "aplicabilidadeMargemPreferenciaAdicional": false,
    "percentualMargemPreferenciaNormal": null,
    "percentualMargemPreferenciaAdicional": null,
    "ncmNbsCodigo": null,
    "ncmNbsDescricao": null,
    "catalogo": null,
    "categoriaItemCatalogo": null,
    "catalogoCodigoItem": null,
    "informacaoComplementar": null,
    "tipoMargemPreferencia": null,
    "exigenciaConteudoNacional": false
  },
  {
    "numeroItem": 30,
    "descricao": "HD Externo 1TB USB 3.0",
    "materialOuServico": "M",
    "materialOuServicoNome": "Material",
    "valorUnitarioEstimado": 478.5,
    "valorTotal": 9570.0,
    "quantidade": 20.0,
    "unidadeMedida": "UNIDADE",
    "orcamentoSigiloso": false,
    "itemCategoriaId": 3,
    "itemCategoriaNome": "Não se aplica",
    "patrimonio": null,
    "codigoRegistroImobiliario": null,
    "criterioJulgamentoId": 1,
    "criterioJulgamentoNome": "Menor preço",
    "situacaoCompraItem": 1,
    "situacaoCompraItemNome": "Em andamento",
    "tipoBeneficio": 1,
    "tipoBeneficioNome": "Participação exclusiva para ME/EPP",
    "incentivoProdutivoBasico": false,
    "dataInclusao": "2026-03-11T08:31:22",
    "dataAtualizacao": "2026-03-11T08:31:22",
    "temResultado": false,
    "imagem": 0,
    "aplicabilidadeMargemPreferenciaNormal": false,
    "aplicabilidadeMargemPreferenciaAdicional": false,
    "percentualMargemPreferenciaNormal": null,
    "percentualMargemPreferenciaAdicional": null,
    "ncmNbsCodigo": null,
    "ncmNbsDescricao": null,
    "catalogo": null,
    "categoriaItemCatalogo": null,
    "catalogoCodigoItem": null,
    "informacaoComplementar": null,
    "tipoMargemPreferencia": null,
    "exigenciaConteudoNacional": false
  },
  {
    "numeroItem": 31,
    "descricao": "Cabos de Energia para Fonte ATX",
    "materialOuServico": "M",
    "materialOuServicoNome": "Material",
    "valorUnitarioEstimado": 56.32,
    "valorTotal": 1689.6,
    "quantidade": 30.0,
    "unidadeMedida": "UNIDADE",
    "orcamentoSigiloso": false,
    "itemCategoriaId": 3,
    "itemCategoriaNome": "Não se aplica",
    "patrimonio": null,
    "codigoRegistroImobiliario": null,
    "criterioJulgamentoId": 1,
    "criterioJulgamentoNome": "Menor preço",
    "situacaoCompraItem": 1,
    "situacaoCompraItemNome": "Em andamento",
    "tipoBeneficio": 1,
    "tipoBeneficioNome": "Participação exclusiva para ME/EPP",
    "incentivoProdutivoBasico": false,
    "dataInclusao": "2026-03-11T08:31:22",
    "dataAtualizacao": "2026-03-11T08:31:22",
    "temResultado": false,
    "imagem": 0,
    "aplicabilidadeMargemPreferenciaNormal": false,
    "aplicabilidadeMargemPreferenciaAdicional": false,
    "percentualMargemPreferenciaNormal": null,
    "percentualMargemPreferenciaAdicional": null,
    "ncmNbsCodigo": null,
    "ncmNbsDescricao": null,
    "catalogo": null,
    "categoriaItemCatalogo": null,
    "catalogoCodigoItem": null,
    "informacaoComplementar": null,
    "tipoMargemPreferencia": null,
    "exigenciaConteudoNacional": false
  },
  {
    "numeroItem": 32,
    "descricao": "Teclado de Notebook",
    "materialOuServico": "M",
    "materialOuServicoNome": "Material",
    "valorUnitarioEstimado": 60.66,
    "valorTotal": 303.3,
    "quantidade": 5.0,
    "unidadeMedida": "UNIDADE",
    "orcamentoSigiloso": false,
    "itemCategoriaId": 3,
    "itemCategoriaNome": "Não se aplica",
    "patrimonio": null,
    "codigoRegistroImobiliario": null,
    "criterioJulgamentoId": 1,
    "criterioJulgamentoNome": "Menor preço",
    "situacaoCompraItem": 1,
    "situacaoCompraItemNome": "Em andamento",
    "tipoBeneficio": 1,
    "tipoBeneficioNome": "Participação exclusiva para ME/EPP",
    "incentivoProdutivoBasico": false,
    "dataInclusao": "2026-03-11T08:31:22",
    "dataAtualizacao": "2026-03-11T08:31:22",
    "temResultado": false,
    "imagem": 0,
    "aplicabilidadeMargemPreferenciaNormal": false,
    "aplicabilidadeMargemPreferenciaAdicional": false,
    "percentualMargemPreferenciaNormal": null,
    "percentualMargemPreferenciaAdicional": null,
    "ncmNbsCodigo": null,
    "ncmNbsDescricao": null,
    "catalogo": null,
    "categoriaItemCatalogo": null,
    "catalogoCodigoItem": null,
    "informacaoComplementar": null,
    "tipoMargemPreferencia": null,
    "exigenciaConteudoNacional": false
  },
  {
    "numeroItem": 33,
    "descricao": "Teclado de Notebook.",
    "materialOuServico": "M",
    "materialOuServicoNome": "Material",
    "valorUnitarioEstimado": 214.67,
    "valorTotal": 1073.35,
    "quantidade": 5.0,
    "unidadeMedida": "UNIDADE",
    "orcamentoSigiloso": false,
    "itemCategoriaId": 3,
    "itemCategoriaNome": "Não se aplica",
    "patrimonio": null,
    "codigoRegistroImobiliario": null,
    "criterioJulgamentoId": 1,
    "criterioJulgamentoNome": "Menor preço",
    "situacaoCompraItem": 1,
    "situacaoCompraItemNome": "Em andamento",
    "tipoBeneficio": 1,
    "tipoBeneficioNome": "Participação exclusiva para ME/EPP",
    "incentivoProdutivoBasico": false,
    "dataInclusao": "2026-03-11T08:31:22",
    "dataAtualizacao": "2026-03-11T08:31:22",
    "temResultado": false,
    "imagem": 0,
    "aplicabilidadeMargemPreferenciaNormal": false,
    "aplicabilidadeMargemPreferenciaAdicional": false,
    "percentualMargemPreferenciaNormal": null,
    "percentualMargemPreferenciaAdicional": null,
    "ncmNbsCodigo": null,
    "ncmNbsDescricao": null,
    "catalogo": null,
    "categoriaItemCatalogo": null,
    "catalogoCodigoItem": null,
    "informacaoComplementar": null,
    "tipoMargemPreferencia": null,
    "exigenciaConteudoNacional": false
  },
  {
    "numeroItem": 34,
    "descricao": "]Teclado de Notebook",
    "materialOuServico": "M",
    "materialOuServicoNome": "Material",
    "valorUnitarioEstimado": 426.9,
    "valorTotal": 2134.5,
    "quantidade": 5.0,
    "unidadeMedida": "UNIDADE",
    "orcamentoSigiloso": false,
    "itemCategoriaId": 3,
    "itemCategoriaNome": "Não se aplica",
    "patrimonio": null,
    "codigoRegistroImobiliario": null,
    "criterioJulgamentoId": 1,
    "criterioJulgamentoNome": "Menor preço",
    "situacaoCompraItem": 1,
    "situacaoCompraItemNome": "Em andamento",
    "tipoBeneficio": 1,
    "tipoBeneficioNome": "Participação exclusiva para ME/EPP",
    "incentivoProdutivoBasico": false,
    "dataInclusao": "2026-03-11T08:31:22",
    "dataAtualizacao": "2026-03-11T08:31:22",
    "temResultado": false,
    "imagem": 0,
    "aplicabilidadeMargemPreferenciaNormal": false,
    "aplicabilidadeMargemPreferenciaAdicional": false,
    "percentualMargemPreferenciaNormal": null,
    "percentualMargemPreferenciaAdicional": null,
    "ncmNbsCodigo": null,
    "ncmNbsDescricao": null,
    "catalogo": null,
    "categoriaItemCatalogo": null,
    "catalogoCodigoItem": null,
    "informacaoComplementar": null,
    "tipoMargemPreferencia": null,
    "exigenciaConteudoNacional": false
  },
  {
    "numeroItem": 35,
    "descricao": "Teclados de Notebooks",
    "materialOuServico": "M",
    "materialOuServicoNome": "Material",
    "valorUnitarioEstimado": 254.83,
    "valorTotal": 764.49,
    "quantidade": 3.0,
    "unidadeMedida": "UNIDADE",
    "orcamentoSigiloso": false,
    "itemCategoriaId": 3,
    "itemCategoriaNome": "Não se aplica",
    "patrimonio": null,
    "codigoRegistroImobiliario": null,
    "criterioJulgamentoId": 1,
    "criterioJulgamentoNome": "Menor preço",
    "situacaoCompraItem": 1,
    "situacaoCompraItemNome": "Em andamento",
    "tipoBeneficio": 1,
    "tipoBeneficioNome": "Participação exclusiva para ME/EPP",
    "incentivoProdutivoBasico": false,
    "dataInclusao": "2026-03-11T08:31:22",
    "dataAtualizacao": "2026-03-11T08:31:22",
    "temResultado": false,
    "imagem": 0,
    "aplicabilidadeMargemPreferenciaNormal": false,
    "aplicabilidadeMargemPreferenciaAdicional": false,
    "percentualMargemPreferenciaNormal": null,
    "percentualMargemPreferenciaAdicional": null,
    "ncmNbsCodigo": null,
    "ncmNbsDescricao": null,
    "catalogo": null,
    "categoriaItemCatalogo": null,
    "catalogoCodigoItem": null,
    "informacaoComplementar": null,
    "tipoMargemPreferencia": null,
    "exigenciaConteudoNacional": false
  },
  {
    "numeroItem": 36,
    "descricao": "Baterias originais/compatíveis para notebooks",
    "materialOuServico": "M",
    "materialOuServicoNome": "Material",
    "valorUnitarioEstimado": 323.28,
    "valorTotal": 1616.4,
    "quantidade": 5.0,
    "unidadeMedida": "UNIDADE",
    "orcamentoSigiloso": false,
    "itemCategoriaId": 3,
    "itemCategoriaNome": "Não se aplica",
    "patrimonio": null,
    "codigoRegistroImobiliario": null,
    "criterioJulgamentoId": 1,
    "criterioJulgamentoNome": "Menor preço",
    "situacaoCompraItem": 1,
    "situacaoCompraItemNome": "Em andamento",
    "tipoBeneficio": 1,
    "tipoBeneficioNome": "Participação exclusiva para ME/EPP",
    "incentivoProdutivoBasico": false,
    "dataInclusao": "2026-03-11T08:31:22",
    "dataAtualizacao": "2026-03-11T08:31:22",
    "temResultado": false,
    "imagem": 0,
    "aplicabilidadeMargemPreferenciaNormal": false,
    "aplicabilidadeMargemPreferenciaAdicional": false,
    "percentualMargemPreferenciaNormal": null,
    "percentualMargemPreferenciaAdicional": null,
    "ncmNbsCodigo": null,
    "ncmNbsDescricao": null,
    "catalogo": null,
    "categoriaItemCatalogo": null,
    "catalogoCodigoItem": null,
    "informacaoComplementar": null,
    "tipoMargemPreferencia": null,
    "exigenciaConteudoNacional": false
  },
  {
    "numeroItem": 37,
    "descricao": "Baterias originais/compatíveis para notebooks.",
    "materialOuServico": "M",
    "materialOuServicoNome": "Material",
    "valorUnitarioEstimado": 403.69,
    "valorTotal": 2018.45,
    "quantidade": 5.0,
    "unidadeMedida": "UNIDADE",
    "orcamentoSigiloso": false,
    "itemCategoriaId": 3,
    "itemCategoriaNome": "Não se aplica",
    "patrimonio": null,
    "codigoRegistroImobiliario": null,
    "criterioJulgamentoId": 1,
    "criterioJulgamentoNome": "Menor preço",
    "situacaoCompraItem": 1,
    "situacaoCompraItemNome": "Em andamento",
    "tipoBeneficio": 1,
    "tipoBeneficioNome": "Participação exclusiva para ME/EPP",
    "incentivoProdutivoBasico": false,
    "dataInclusao": "2026-03-11T08:31:22",
    "dataAtualizacao": "2026-03-11T08:31:22",
    "temResultado": false,
    "imagem": 0,
    "aplicabilidadeMargemPreferenciaNormal": false,
    "aplicabilidadeMargemPreferenciaAdicional": false,
    "percentualMargemPreferenciaNormal": null,
    "percentualMargemPreferenciaAdicional": null,
    "ncmNbsCodigo": null,
    "ncmNbsDescricao": null,
    "catalogo": null,
    "categoriaItemCatalogo": null,
    "catalogoCodigoItem": null,
    "informacaoComplementar": null,
    "tipoMargemPreferencia": null,
    "exigenciaConteudoNacional": false
  },
  {
    "numeroItem": 38,
    "descricao": "Baterias originais/compatíveis para notebooks,",
    "materialOuServico": "M",
    "materialOuServicoNome": "Material",
    "valorUnitarioEstimado": 366.79,
    "valorTotal": 1100.37,
    "quantidade": 3.0,
    "unidadeMedida": "UNIDADE",
    "orcamentoSigiloso": false,
    "itemCategoriaId": 3,
    "itemCategoriaNome": "Não se aplica",
    "patrimonio": null,
    "codigoRegistroImobiliario": null,
    "criterioJulgamentoId": 1,
    "criterioJulgamentoNome": "Menor preço",
    "situacaoCompraItem": 1,
    "situacaoCompraItemNome": "Em andamento",
    "tipoBeneficio": 1,
    "tipoBeneficioNome": "Participação exclusiva para ME/EPP",
    "incentivoProdutivoBasico": false,
    "dataInclusao": "2026-03-11T08:31:22",
    "dataAtualizacao": "2026-03-11T08:31:22",
    "temResultado": false,
    "imagem": 0,
    "aplicabilidadeMargemPreferenciaNormal": false,
    "aplicabilidadeMargemPreferenciaAdicional": false,
    "percentualMargemPreferenciaNormal": null,
    "percentualMargemPreferenciaAdicional": null,
    "ncmNbsCodigo": null,
    "ncmNbsDescricao": null,
    "catalogo": null,
    "categoriaItemCatalogo": null,
    "catalogoCodigoItem": null,
    "informacaoComplementar": null,
    "tipoMargemPreferencia": null,
    "exigenciaConteudoNacional": false
  },
  {
    "numeroItem": 39,
    "descricao": "Baterias originais/compatíveis para notebookss",
    "materialOuServico": "M",
    "materialOuServicoNome": "Material",
    "valorUnitarioEstimado": 323.28,
    "valorTotal": 969.84,
    "quantidade": 3.0,
    "unidadeMedida": "UNIDADE",
    "orcamentoSigiloso": false,
    "itemCategoriaId": 3,
    "itemCategoriaNome": "Não se aplica",
    "patrimonio": null,
    "codigoRegistroImobiliario": null,
    "criterioJulgamentoId": 1,
    "criterioJulgamentoNome": "Menor preço",
    "situacaoCompraItem": 1,
    "situacaoCompraItemNome": "Em andamento",
    "tipoBeneficio": 1,
    "tipoBeneficioNome": "Participação exclusiva para ME/EPP",
    "incentivoProdutivoBasico": false,
    "dataInclusao": "2026-03-11T08:31:22",
    "dataAtualizacao": "2026-03-11T08:31:22",
    "temResultado": false,
    "imagem": 0,
    "aplicabilidadeMargemPreferenciaNormal": false,
    "aplicabilidadeMargemPreferenciaAdicional": false,
    "percentualMargemPreferenciaNormal": null,
    "percentualMargemPreferenciaAdicional": null,
    "ncmNbsCodigo": null,
    "ncmNbsDescricao": null,
    "catalogo": null,
    "categoriaItemCatalogo": null,
    "catalogoCodigoItem": null,
    "informacaoComplementar": null,
    "tipoMargemPreferencia": null,
    "exigenciaConteudoNacional": false
  },
  {
    "numeroItem": 40,
    "descricao": "Bateria selada VRLA para Nobreaks",
    "materialOuServico": "M",
    "materialOuServicoNome": "Material",
    "valorUnitarioEstimado": 191.67,
    "valorTotal": 1341.69,
    "quantidade": 7.0,
    "unidadeMedida": "UNIDADE",
    "orcamentoSigiloso": false,
    "itemCategoriaId": 3,
    "itemCategoriaNome": "Não se aplica",
    "patrimonio": null,
    "codigoRegistroImobiliario": null,
    "criterioJulgamentoId": 1,
    "criterioJulgamentoNome": "Menor preço",
    "situacaoCompraItem": 1,
    "situacaoCompraItemNome": "Em andamento",
    "tipoBeneficio": 1,
    "tipoBeneficioNome": "Participação exclusiva para ME/EPP",
    "incentivoProdutivoBasico": false,
    "dataInclusao": "2026-03-11T08:31:22",
    "dataAtualizacao": "2026-03-11T08:31:22",
    "temResultado": false,
    "imagem": 0,
    "aplicabilidadeMargemPreferenciaNormal": false,
    "aplicabilidadeMargemPreferenciaAdicional": false,
    "percentualMargemPreferenciaNormal": null,
    "percentualMargemPreferenciaAdicional": null,
    "ncmNbsCodigo": null,
    "ncmNbsDescricao": null,
    "catalogo": null,
    "categoriaItemCatalogo": null,
    "catalogoCodigoItem": null,
    "informacaoComplementar": null,
    "tipoMargemPreferencia": null,
    "exigenciaConteudoNacional": false
  },
  {
    "numeroItem": 41,
    "descricao": "Carregadores/ Fontes de alimentação",
    "materialOuServico": "M",
    "materialOuServicoNome": "Material",
    "valorUnitarioEstimado": 160.22,
    "valorTotal": 1121.54,
    "quantidade": 7.0,
    "unidadeMedida": "UNIDADE",
    "orcamentoSigiloso": false,
    "itemCategoriaId": 3,
    "itemCategoriaNome": "Não se aplica",
    "patrimonio": null,
    "codigoRegistroImobiliario": null,
    "criterioJulgamentoId": 1,
    "criterioJulgamentoNome": "Menor preço",
    "situacaoCompraItem": 1,
    "situacaoCompraItemNome": "Em andamento",
    "tipoBeneficio": 1,
    "tipoBeneficioNome": "Participação exclusiva para ME/EPP",
    "incentivoProdutivoBasico": false,
    "dataInclusao": "2026-03-11T08:31:22",
    "dataAtualizacao": "2026-03-11T08:31:22",
    "temResultado": false,
    "imagem": 0,
    "aplicabilidadeMargemPreferenciaNormal": false,
    "aplicabilidadeMargemPreferenciaAdicional": false,
    "percentualMargemPreferenciaNormal": null,
    "percentualMargemPreferenciaAdicional": null,
    "ncmNbsCodigo": null,
    "ncmNbsDescricao": null,
    "catalogo": null,
    "categoriaItemCatalogo": null,
    "catalogoCodigoItem": null,
    "informacaoComplementar": null,
    "tipoMargemPreferencia": null,
    "exigenciaConteudoNacional": false
  },
  {
    "numeroItem": 42,
    "descricao": "Carregadores/ Fontes de alimentação.",
    "materialOuServico": "M",
    "materialOuServicoNome": "Material",
    "valorUnitarioEstimado": 209.67,
    "valorTotal": 629.01,
    "quantidade": 3.0,
    "unidadeMedida": "UNIDADE",
    "orcamentoSigiloso": false,
    "itemCategoriaId": 3,
    "itemCategoriaNome": "Não se aplica",
    "patrimonio": null,
    "codigoRegistroImobiliario": null,
    "criterioJulgamentoId": 1,
    "criterioJulgamentoNome": "Menor preço",
    "situacaoCompraItem": 1,
    "situacaoCompraItemNome": "Em andamento",
    "tipoBeneficio": 1,
    "tipoBeneficioNome": "Participação exclusiva para ME/EPP",
    "incentivoProdutivoBasico": false,
    "dataInclusao": "2026-03-11T08:31:22",
    "dataAtualizacao": "2026-03-11T08:31:22",
    "temResultado": false,
    "imagem": 0,
    "aplicabilidadeMargemPreferenciaNormal": false,
    "aplicabilidadeMargemPreferenciaAdicional": false,
    "percentualMargemPreferenciaNormal": null,
    "percentualMargemPreferenciaAdicional": null,
    "ncmNbsCodigo": null,
    "ncmNbsDescricao": null,
    "catalogo": null,
    "categoriaItemCatalogo": null,
    "catalogoCodigoItem": null,
    "informacaoComplementar": null,
    "tipoMargemPreferencia": null,
    "exigenciaConteudoNacional": false
  },
  {
    "numeroItem": 43,
    "descricao": "Carregadores/ Fontes de alimentação,",
    "materialOuServico": "M",
    "materialOuServicoNome": "Material",
    "valorUnitarioEstimado": 209.67,
    "valorTotal": 629.01,
    "quantidade": 3.0,
    "unidadeMedida": "UNIDADE",
    "orcamentoSigiloso": false,
    "itemCategoriaId": 3,
    "itemCategoriaNome": "Não se aplica",
    "patrimonio": null,
    "codigoRegistroImobiliario": null,
    "criterioJulgamentoId": 1,
    "criterioJulgamentoNome": "Menor preço",
    "situacaoCompraItem": 1,
    "situacaoCompraItemNome": "Em andamento",
    "tipoBeneficio": 1,
    "tipoBeneficioNome": "Participação exclusiva para ME/EPP",
    "incentivoProdutivoBasico": false,
    "dataInclusao": "2026-03-11T08:31:22",
    "dataAtualizacao": "2026-03-11T08:31:22",
    "temResultado": false,
    "imagem": 0,
    "aplicabilidadeMargemPreferenciaNormal": false,
    "aplicabilidadeMargemPreferenciaAdicional": false,
    "percentualMargemPreferenciaNormal": null,
    "percentualMargemPreferenciaAdicional": null,
    "ncmNbsCodigo": null,
    "ncmNbsDescricao": null,
    "catalogo": null,
    "categoriaItemCatalogo": null,
    "catalogoCodigoItem": null,
    "informacaoComplementar": null,
    "tipoMargemPreferencia": null,
    "exigenciaConteudoNacional": false
  },
  {
    "numeroItem": 44,
    "descricao": "Carregadores/ Fontes de alimentação-",
    "materialOuServico": "M",
    "materialOuServicoNome": "Material",
    "valorUnitarioEstimado": 160.22,
    "valorTotal": 480.66,
    "quantidade": 3.0,
    "unidadeMedida": "UNIDADE",
    "orcamentoSigiloso": false,
    "itemCategoriaId": 3,
    "itemCategoriaNome": "Não se aplica",
    "patrimonio": null,
    "codigoRegistroImobiliario": null,
    "criterioJulgamentoId": 1,
    "criterioJulgamentoNome": "Menor preço",
    "situacaoCompraItem": 1,
    "situacaoCompraItemNome": "Em andamento",
    "tipoBeneficio": 1,
    "tipoBeneficioNome": "Participação exclusiva para ME/EPP",
    "incentivoProdutivoBasico": false,
    "dataInclusao": "2026-03-11T08:31:22",
    "dataAtualizacao": "2026-03-11T08:31:22",
    "temResultado": false,
    "imagem": 0,
    "aplicabilidadeMargemPreferenciaNormal": false,
    "aplicabilidadeMargemPreferenciaAdicional": false,
    "percentualMargemPreferenciaNormal": null,
    "percentualMargemPreferenciaAdicional": null,
    "ncmNbsCodigo": null,
    "ncmNbsDescricao": null,
    "catalogo": null,
    "categoriaItemCatalogo": null,
    "catalogoCodigoItem": null,
    "informacaoComplementar": null,
    "tipoMargemPreferencia": null,
    "exigenciaConteudoNacional": false
  },
  {
    "numeroItem": 45,
    "descricao": "Coolers/ventoinhas para notebooks",
    "materialOuServico": "M",
    "materialOuServicoNome": "Material",
    "valorUnitarioEstimado": 95.0,
    "valorTotal": 285.0,
    "quantidade": 3.0,
    "unidadeMedida": "UNIDADE",
    "orcamentoSigiloso": false,
    "itemCategoriaId": 3,
    "itemCategoriaNome": "Não se aplica",
    "patrimonio": null,
    "codigoRegistroImobiliario": null,
    "criterioJulgamentoId": 1,
    "criterioJulgamentoNome": "Menor preço",
    "situacaoCompraItem": 1,
    "situacaoCompraItemNome": "Em andamento",
    "tipoBeneficio": 1,
    "tipoBeneficioNome": "Participação exclusiva para ME/EPP",
    "incentivoProdutivoBasico": false,
    "dataInclusao": "2026-03-11T08:31:22",
    "dataAtualizacao": "2026-03-11T08:31:22",
    "temResultado": false,
    "imagem": 0,
    "aplicabilidadeMargemPreferenciaNormal": false,
    "aplicabilidadeMargemPreferenciaAdicional": false,
    "percentualMargemPreferenciaNormal": null,
    "percentualMargemPreferenciaAdicional": null,
    "ncmNbsCodigo": null,
    "ncmNbsDescricao": null,
    "catalogo": null,
    "categoriaItemCatalogo": null,
    "catalogoCodigoItem": null,
    "informacaoComplementar": null,
    "tipoMargemPreferencia": null,
    "exigenciaConteudoNacional": false
  },
  {
    "numeroItem": 46,
    "descricao": "Coolers/ventoinhas paraa notebooks",
    "materialOuServico": "M",
    "materialOuServicoNome": "Material",
    "valorUnitarioEstimado": 95.0,
    "valorTotal": 285.0,
    "quantidade": 3.0,
    "unidadeMedida": "UNIDADE",
    "orcamentoSigiloso": false,
    "itemCategoriaId": 3,
    "itemCategoriaNome": "Não se aplica",
    "patrimonio": null,
    "codigoRegistroImobiliario": null,
    "criterioJulgamentoId": 1,
    "criterioJulgamentoNome": "Menor preço",
    "situacaoCompraItem": 1,
    "situacaoCompraItemNome": "Em andamento",
    "tipoBeneficio": 1,
    "tipoBeneficioNome": "Participação exclusiva para ME/EPP",
    "incentivoProdutivoBasico": false,
    "dataInclusao": "2026-03-11T08:31:22",
    "dataAtualizacao": "2026-03-11T08:31:22",
    "temResultado": false,
    "imagem": 0,
    "aplicabilidadeMargemPreferenciaNormal": false,
    "aplicabilidadeMargemPreferenciaAdicional": false,
    "percentualMargemPreferenciaNormal": null,
    "percentualMargemPreferenciaAdicional": null,
    "ncmNbsCodigo": null,
    "ncmNbsDescricao": null,
    "catalogo": null,
    "categoriaItemCatalogo": null,
    "catalogoCodigoItem": null,
    "informacaoComplementar": null,
    "tipoMargemPreferencia": null,
    "exigenciaConteudoNacional": false
  },
  {
    "numeroItem": 47,
    "descricao": "Coolers/ventoinhas para notebooks ..",
    "materialOuServico": "M",
    "materialOuServicoNome": "Material",
    "valorUnitarioEstimado": 95.0,
    "valorTotal": 285.0,
    "quantidade": 3.0,
    "unidadeMedida": "UNIDADE",
    "orcamentoSigiloso": false,
    "itemCategoriaId": 3,
    "itemCategoriaNome": "Não se aplica",
    "patrimonio": null,
    "codigoRegistroImobiliario": null,
    "criterioJulgamentoId": 1,
    "criterioJulgamentoNome": "Menor preço",
    "situacaoCompraItem": 1,
    "situacaoCompraItemNome": "Em andamento",
    "tipoBeneficio": 1,
    "tipoBeneficioNome": "Participação exclusiva para ME/EPP",
    "incentivoProdutivoBasico": false,
    "dataInclusao": "2026-03-11T08:31:22",
    "dataAtualizacao": "2026-03-11T08:31:22",
    "temResultado": false,
    "imagem": 0,
    "aplicabilidadeMargemPreferenciaNormal": false,
    "aplicabilidadeMargemPreferenciaAdicional": false,
    "percentualMargemPreferenciaNormal": null,
    "percentualMargemPreferenciaAdicional": null,
    "ncmNbsCodigo": null,
    "ncmNbsDescricao": null,
    "catalogo": null,
    "categoriaItemCatalogo": null,
    "catalogoCodigoItem": null,
    "informacaoComplementar": null,
    "tipoMargemPreferencia": null,
    "exigenciaConteudoNacional": false
  },
  {
    "numeroItem": 48,
    "descricao": "Coolers/ventoinhas para notebooks.,",
    "materialOuServico": "M",
    "materialOuServicoNome": "Material",
    "valorUnitarioEstimado": 95.0,
    "valorTotal": 285.0,
    "quantidade": 3.0,
    "unidadeMedida": "UNIDADE",
    "orcamentoSigiloso": false,
    "itemCategoriaId": 3,
    "itemCategoriaNome": "Não se aplica",
    "patrimonio": null,
    "codigoRegistroImobiliario": null,
    "criterioJulgamentoId": 1,
    "criterioJulgamentoNome": "Menor preço",
    "situacaoCompraItem": 1,
    "situacaoCompraItemNome": "Em andamento",
    "tipoBeneficio": 1,
    "tipoBeneficioNome": "Participação exclusiva para ME/EPP",
    "incentivoProdutivoBasico": false,
    "dataInclusao": "2026-03-11T08:31:22",
    "dataAtualizacao": "2026-03-11T08:31:22",
    "temResultado": false,
    "imagem": 0,
    "aplicabilidadeMargemPreferenciaNormal": false,
    "aplicabilidadeMargemPreferenciaAdicional": false,
    "percentualMargemPreferenciaNormal": null,
    "percentualMargemPreferenciaAdicional": null,
    "ncmNbsCodigo": null,
    "ncmNbsDescricao": null,
    "catalogo": null,
    "categoriaItemCatalogo": null,
    "catalogoCodigoItem": null,
    "informacaoComplementar": null,
    "tipoMargemPreferencia": null,
    "exigenciaConteudoNacional": false
  },
  {
    "numeroItem": 49,
    "descricao": "Bateria Bios Cr2032 3v com Conector",
    "materialOuServico": "M",
    "materialOuServicoNome": "Material",
    "valorUnitarioEstimado": 18.66,
    "valorTotal": 559.8,
    "quantidade": 30.0,
    "unidadeMedida": "CARTELA",
    "orcamentoSigiloso": false,
    "itemCategoriaId": 3,
    "itemCategoriaNome": "Não se aplica",
    "patrimonio": null,
    "codigoRegistroImobiliario": null,
    "criterioJulgamentoId": 1,
    "criterioJulgamentoNome": "Menor preço",
    "situacaoCompraItem": 1,
    "situacaoCompraItemNome": "Em andamento",
    "tipoBeneficio": 1,
    "tipoBeneficioNome": "Participação exclusiva para ME/EPP",
    "incentivoProdutivoBasico": false,
    "dataInclusao": "2026-03-11T08:31:22",
    "dataAtualizacao": "2026-03-11T08:31:22",
    "temResultado": false,
    "imagem": 0,
    "aplicabilidadeMargemPreferenciaNormal": false,
    "aplicabilidadeMargemPreferenciaAdicional": false,
    "percentualMargemPreferenciaNormal": null,
    "percentualMargemPreferenciaAdicional": null,
    "ncmNbsCodigo": null,
    "ncmNbsDescricao": null,
    "catalogo": null,
    "categoriaItemCatalogo": null,
    "catalogoCodigoItem": null,
    "informacaoComplementar": null,
    "tipoMargemPreferencia": null,
    "exigenciaConteudoNacional": false
  },
  {
    "numeroItem": 50,
    "descricao": "Bateria 3V Lithium",
    "materialOuServico": "M",
    "materialOuServicoNome": "Material",
    "valorUnitarioEstimado": 16.33,
    "valorTotal": 489.9,
    "quantidade": 30.0,
    "unidadeMedida": "CARTELA",
    "orcamentoSigiloso": false,
    "itemCategoriaId": 3,
    "itemCategoriaNome": "Não se aplica",
    "patrimonio": null,
    "codigoRegistroImobiliario": null,
    "criterioJulgamentoId": 1,
    "criterioJulgamentoNome": "Menor preço",
    "situacaoCompraItem": 1,
    "situacaoCompraItemNome": "Em andamento",
    "tipoBeneficio": 1,
    "tipoBeneficioNome": "Participação exclusiva para ME/EPP",
    "incentivoProdutivoBasico": false,
    "dataInclusao": "2026-03-11T08:31:22",
    "dataAtualizacao": "2026-03-11T08:31:22",
    "temResultado": false,
    "imagem": 0,
    "aplicabilidadeMargemPreferenciaNormal": false,
    "aplicabilidadeMargemPreferenciaAdicional": false,
    "percentualMargemPreferenciaNormal": null,
    "percentualMargemPreferenciaAdicional": null,
    "ncmNbsCodigo": null,
    "ncmNbsDescricao": null,
    "catalogo": null,
    "categoriaItemCatalogo": null,
    "catalogoCodigoItem": null,
    "informacaoComplementar": null,
    "tipoMargemPreferencia": null,
    "exigenciaConteudoNacional": false
  }
]